MANIFEST.in
README.txt
setup.cfg
setup.py
docs/HISTORY.txt
docs/INSTALL.txt
docs/LICENSE.GPL
docs/LICENSE.txt
ityou/__init__.py
ityou.whoisonline.egg-info/PKG-INFO
ityou.whoisonline.egg-info/SOURCES.txt
ityou.whoisonline.egg-info/dependency_links.txt
ityou.whoisonline.egg-info/entry_points.txt
ityou.whoisonline.egg-info/namespace_packages.txt
ityou.whoisonline.egg-info/not-zip-safe
ityou.whoisonline.egg-info/paster_plugins.txt
ityou.whoisonline.egg-info/requires.txt
ityou.whoisonline.egg-info/top_level.txt
ityou/whoisonline/Install.py
ityou/whoisonline/__init__.py
ityou/whoisonline/config.py
ityou/whoisonline/configure.zcml
ityou/whoisonline/dbapi.py
ityou/whoisonline/interfaces.py
ityou/whoisonline/tests.py
ityou/whoisonline/translate.sh
ityou/whoisonline/viewlets.py
ityou/whoisonline/whoisonline-tracking.pt
ityou/whoisonline/Extensions/Install.py
ityou/whoisonline/Extensions/__init__.py
ityou/whoisonline/locales/extra.pot
ityou/whoisonline/locales/ityou.whoisonline.pot
ityou/whoisonline/locales/de/LC_MESSAGES/extra.po
ityou/whoisonline/locales/de/LC_MESSAGES/ityou.whoisonline.po
ityou/whoisonline/locales/en/README.txt
ityou/whoisonline/locales/en/LC_MESSAGES/extra.po
ityou/whoisonline/locales/en/LC_MESSAGES/ityou.whoisonline.po
ityou/whoisonline/portlets/__init__.py
ityou/whoisonline/portlets/ajax.py
ityou/whoisonline/portlets/configure.zcml
ityou/whoisonline/portlets/controlpanel.py
ityou/whoisonline/portlets/utils.py
ityou/whoisonline/portlets/whoami.pt
ityou/whoisonline/portlets/whoami.py
ityou/whoisonline/portlets/whoisonline-ajax.pt
ityou/whoisonline/portlets/whoisonline.pt
ityou/whoisonline/portlets/whoisonline.py
ityou/whoisonline/portlets/resources/_jquery.hoverIntent.minified.js
ityou/whoisonline/portlets/resources/_jquery.tmpl.min.js
ityou/whoisonline/portlets/resources/_whoisonline-jq.js
ityou/whoisonline/portlets/resources/arrow-top.png
ityou/whoisonline/portlets/resources/bar.gif
ityou/whoisonline/portlets/resources/console-active-icon.png
ityou/whoisonline/portlets/resources/console-icon.png
ityou/whoisonline/portlets/resources/folder-active-icon.png
ityou/whoisonline/portlets/resources/folder-icon.png
ityou/whoisonline/portlets/resources/ityou-esi-whoisonline-icon.png
ityou/whoisonline/portlets/resources/profile-active-icon.png
ityou/whoisonline/portlets/resources/profile-icon.png
