Metadata-Version: 1.1
Name: ityou.whoisonline
Version: 1.3.1
Summary: Plone Product - Show users who are online
Home-page: http://www.ityou.de/esi/
Author: ITYOU/LM
Author-email: lm@ityou.de
License: GPL
Keywords: Plone Who Online
Platform: UNKNOWN
Classifier: Framework :: Plone
Classifier: Programming Language :: Python
